{"mensagens": 
    {
        "illrauga": {
            "titulo": "illrauga",
            "descricao": "“A criatura citada no artigo a seguir é uma criação original idealizada pela equipe Samurai Edge, não tendo nenhuma relação com a mitologia nórdica mas sim tendo sua idealização baseada na mesma”",
            "texto": "São criaturas numerosas que se comportam como enxames, suas características físicas possuem ambos aspectos de uma serpente e de um morcego \n. 
            Eles se originam através das lágrimas de ódio e tristeza dos humanos mortos que ficam no Hel e devido a isso, é uma tradição de enterrar os mortos com ambos os olhos fechados, para assim evitar que esse processo seja retardado ou até mesmo evitado. \n 
            Devido a natureza de sua existência, que é unicamente vagar pelo submundo sem destino certo, estas criaturas nascem cegas com a característica mais marcante delas sendo o olho gigantesco que aparenta não ter vida e por causa dessa ausência de visão, eles desenvolveram uma alta sensibilidade com o tato conseguindo identificar os diferentes tipos de toque como de coisas inanimadas e seres vivos, tendo como reação primária atacar qualquer ser vivo que venha entrar em contato consigo. \n
            Também é interpretado que estas criaturas são cegas devido ao sentimento de ódio que é transmitido de seus progenitores.\n De vez em quando esses seres escapam do submundo e vagam pelos outros mundos, geralmente não são bem vistos por ninguém.Seu nome é uma junção de duas palavras, sendo Illr “Mal” ou “Maligno” e Auga não sendo uma palavra direta mas contendo vários significados em relação a “Olhar” ou “Observar”, a tradução literal de seu nome poderia ser algo como “Olhar Maligno”."
        }
    }
}